atlasai/__init__.py
atlasai/cli.py
atlasai/ai/__init__.py
atlasai/ai/ai_agent.py
atlasai/ai/ai_cli.py
atlasai/ai/ai_service.py
atlasai/ai/general_agent.py
atlasai/ai/prompts.py
atlasai/tools/__init__.py
atlasai/tools/tools.py
atlasai_cli-0.2.8.dist-info/licenses/LICENSE
atlasai_cli-0.2.8.dist-info/METADATA
atlasai_cli-0.2.8.dist-info/WHEEL
atlasai_cli-0.2.8.dist-info/entry_points.txt
atlasai_cli-0.2.8.dist-info/top_level.txt
atlasai_cli-0.2.8.dist-info/RECORD
