Metadata-Version: 2.4
Name: atlasai-cli
Version: 0.2.8
Summary: AI-powered CLI for AtlasServer deployments: suggest, optimize & debug commands
Author-email: AtlasServer-Core / Fredy <riveraaai200678@gmail.com>
License:                                  Apache License
Project-URL: Homepage, https://github.com/AtlasServer-Core/AtlasAI-CLI
Project-URL: Repository, https://github.com/AtlasServer-Core/AtlasAI-CLI
Project-URL: Documentation, https://github.com/AtlasServer-Core/AtlasAI-CLI#readme
Project-URL: Issue Tracker, https://github.com/AtlasServer-Core/AtlasAI-CLI/issues
License-File: LICENSE
Requires-Dist: passlib
Requires-Dist: psutil
Requires-Dist: pydantic
Requires-Dist: python-multipart
Requires-Dist: aiofiles
Requires-Dist: click>=8.0.0
Requires-Dist: platformdirs
Requires-Dist: ollama
Requires-Dist: langchain
Requires-Dist: langchain-experimental
Requires-Dist: langchain-community
Requires-Dist: duckduckgo-search
Requires-Dist: openai-agents
Requires-Dist: openai
Requires-Dist: rich
Requires-Dist: anthropic
Dynamic: license-file
